sunshower/__init__.py
sunshower/engine.py
sunshower/schema.py
sunshower/utils.py
pysunshower-0.0.1.dist-info/METADATA
pysunshower-0.0.1.dist-info/WHEEL
pysunshower-0.0.1.dist-info/licenses/LICENSE
pysunshower-0.0.1.dist-info/RECORD
