Metadata-Version: 2.4
Name: pySunshower
Version: 0.0.1
Summary: pySunshower is a Python library for evaluating AI agents in a declarative way
License-Expression: MIT
License-File: LICENSE
Author: Vic Fernandez III
Author-email: victor@deathlabs.io
Requires-Python: >=3.12
Classifier: Programming Language :: Python
Classifier: Topic :: Scientific/Engineering :: Artificial Intelligence
Requires-Dist: langchain (>=1.2.0,<2.0.0)
Requires-Dist: langchain-community (>=0.4.1,<0.5.0)
Requires-Dist: langchain-openai (>=1.1.6,<2.0.0)
Requires-Dist: langgraph (>=1.0.5,<2.0.0)
Requires-Dist: pyyaml (>=6.0.3,<7.0.0)
Requires-Dist: ray (>=2.53.0,<3.0.0)
Project-URL: Homepage, https://github.com/deathlabs/sunshower
Project-URL: Issues, https://github.com/deathlabs/sunshower/issues
